{"code":"import { account, walletClient } from './config'\nimport { domain, types } from './data'\n \nconst signature = await walletClient.signTypedData({ // [!code focus:99]\n  // Account used for signing.\n  account,\n  domain,\n  types,\n  primaryType: 'Mail',\n  message: {\n    from: {\n      name: 'Cow',\n      wallet: '0xCD2a3d9F938E13CD947Ec05AbC7FE734Df8DD826',\n    },\n    to: {\n      name: 'Bob',\n      wallet: '0xbBbBBBBbbBBBbbbBbbBbbbbBBbBbbbbBbBbbBBbB',\n    },\n    contents: 'Hello, Bob!',\n  },\n  // Verifying contract address (e.g. ERC-4337 Smart Account).\n  verifier: '0xCB9fA1eA9b8A3bf422a8639f23Df77ea66020eC2'\n})","nodes":[{"type":"hover","text":"(alias) const account: any\nimport account","start":9,"length":7,"target":"account","line":0,"character":9},{"type":"hover","text":"(alias) const walletClient: any\nimport walletClient","start":18,"length":12,"target":"walletClient","line":0,"character":18},{"type":"hover","text":"(alias) const domain: {\n    readonly name: \"Ether Mail\";\n    readonly version: \"1\";\n    readonly chainId: 1;\n    readonly verifyingContract: \"0xCcCCccccCCCCcCCCCCCcCcCccCcCCCcCcccccccC\";\n}\nimport domain","start":58,"length":6,"target":"domain","line":1,"character":9},{"type":"hover","text":"(alias) const types: {\n    readonly Person: readonly [{\n        readonly name: \"name\";\n        readonly type: \"string\";\n    }, {\n        readonly name: \"wallet\";\n        readonly type: \"address\";\n    }];\n    readonly Mail: readonly [{\n        readonly name: \"from\";\n        readonly type: \"Person\";\n    }, {\n        readonly name: \"to\";\n        readonly type: \"Person\";\n    }, {\n        readonly name: \"contents\";\n        readonly type: \"string\";\n    }];\n}\nimport types","start":66,"length":5,"target":"types","line":1,"character":17},{"type":"hover","text":"const signature: any","start":96,"length":9,"target":"signature","line":3,"character":6},{"type":"hover","text":"(alias) const walletClient: any\nimport walletClient","start":114,"length":12,"target":"walletClient","line":3,"character":24},{"type":"hover","text":"any","start":127,"length":13,"target":"signTypedData","line":3,"character":37},{"type":"hover","text":"(property) account: any","start":196,"length":7,"target":"account","line":5,"character":2},{"type":"hover","text":"(property) domain: {\n    readonly name: \"Ether Mail\";\n    readonly version: \"1\";\n    readonly chainId: 1;\n    readonly verifyingContract: \"0xCcCCccccCCCCcCCCCCCcCcCccCcCCCcCcccccccC\";\n}","start":207,"length":6,"target":"domain","line":6,"character":2},{"type":"hover","text":"(property) types: {\n    readonly Person: readonly [{\n        readonly name: \"name\";\n        readonly type: \"string\";\n    }, {\n        readonly name: \"wallet\";\n        readonly type: \"address\";\n    }];\n    readonly Mail: readonly [{\n        readonly name: \"from\";\n        readonly type: \"Person\";\n    }, {\n        readonly name: \"to\";\n        readonly type: \"Person\";\n    }, {\n        readonly name: \"contents\";\n        readonly type: \"string\";\n    }];\n}","start":217,"length":5,"target":"types","line":7,"character":2},{"type":"hover","text":"(property) primaryType: string","start":226,"length":11,"target":"primaryType","line":8,"character":2},{"type":"hover","text":"(property) message: {\n    from: {\n        name: string;\n        wallet: string;\n    };\n    to: {\n        name: string;\n        wallet: string;\n    };\n    contents: string;\n}","start":249,"length":7,"target":"message","line":9,"character":2},{"type":"hover","text":"(property) from: {\n    name: string;\n    wallet: string;\n}","start":264,"length":4,"target":"from","line":10,"character":4},{"type":"hover","text":"(property) name: string","start":278,"length":4,"target":"name","line":11,"character":6},{"type":"hover","text":"(property) wallet: string","start":297,"length":6,"target":"wallet","line":12,"character":6},{"type":"hover","text":"(property) to: {\n    name: string;\n    wallet: string;\n}","start":362,"length":2,"target":"to","line":14,"character":4},{"type":"hover","text":"(property) name: string","start":374,"length":4,"target":"name","line":15,"character":6},{"type":"hover","text":"(property) wallet: string","start":393,"length":6,"target":"wallet","line":16,"character":6},{"type":"hover","text":"(property) contents: string","start":458,"length":8,"target":"contents","line":18,"character":4},{"type":"hover","text":"(property) verifier: string","start":553,"length":8,"target":"verifier","line":21,"character":2}],"meta":{"extension":"ts","compilerOptions":{"strict":true,"module":99,"target":99,"allowJs":true,"skipDefaultLibCheck":true,"skipLibCheck":true,"moduleDetection":3,"baseUrl":".","ignoreDeprecations":"5.0","moduleResolution":100,"preserveSymlinks":false,"types":["node"]},"handbookOptions":{"errors":[],"noErrors":true,"noErrorsCutted":false,"noErrorValidation":false,"noStaticSemanticInfo":false,"showEmit":false,"keepNotations":false},"removals":[[0,1005]],"flagNotations":[{"type":"tag","name":"log","value":"↑ JSON-RPC Account","start":862,"end":890},{"type":"tag","name":"log","value":"↑ Local Account","start":942,"end":967}],"virtualFiles":[{"offset":0,"filename":"data.ts","filepath":"../data.ts","content":"// @filename: data.ts\n// All properties on a domain are optional\nexport const domain = {\n  name: 'Ether Mail',\n  version: '1',\n  chainId: 1,\n  verifyingContract: '0xCcCCccccCCCCcCCCCCCcCcCccCcCCCcCcccccccC',\n} as const\n \n// The named list of all type definitions\nexport const types = {\n  Person: [\n    { name: 'name', type: 'string' },\n    { name: 'wallet', type: 'address' },\n  ],\n  Mail: [\n    { name: 'from', type: 'Person' },\n    { name: 'to', type: 'Person' },\n    { name: 'contents', type: 'string' },\n  ],\n} as const\n","extension":"ts","supportLsp":true},{"offset":524,"filename":"config.ts","filepath":"../config.ts","content":"// @filename: config.ts\nimport { createWalletClient, http } from 'viem'\nimport { mainnet } from 'viem/chains'\nimport { erc7739Actions } from 'viem/experimental'\n\nexport const walletClient = createWalletClient({\n  chain: mainnet,\n  transport: http(),\n}).extend(erc7739Actions())\n\nexport const [account] = await walletClient.getAddresses()\n// @log: ↑ JSON-RPC Account\n\n// export const account = privateKeyToAccount(...)\n// @log: ↑ Local Account\n","extension":"ts","supportLsp":true},{"offset":967,"filename":"example.ts","filepath":"../example.ts","content":"// @filename: example.ts\n// ---cut---\nimport { account, walletClient } from './config'\nimport { domain, types } from './data'\n \nconst signature = await walletClient.signTypedData({ // [!code focus:99]\n  // Account used for signing.\n  account,\n  domain,\n  types,\n  primaryType: 'Mail',\n  message: {\n    from: {\n      name: 'Cow',\n      wallet: '0xCD2a3d9F938E13CD947Ec05AbC7FE734Df8DD826',\n    },\n    to: {\n      name: 'Bob',\n      wallet: '0xbBbBBBBbbBBBbbbBbbBbbbbBBbBbbbbBbBbbBBbB',\n    },\n    contents: 'Hello, Bob!',\n  },\n  // Verifying contract address (e.g. ERC-4337 Smart Account).\n  verifier: '0xCB9fA1eA9b8A3bf422a8639f23Df77ea66020eC2'\n})","extension":"ts","supportLsp":true}],"positionQueries":[],"positionCompletions":[],"positionHighlights":[]},"queries":[],"completions":[],"errors":[],"highlights":[],"hovers":[{"type":"hover","text":"(alias) const account: any\nimport account","start":9,"length":7,"target":"account","line":0,"character":9},{"type":"hover","text":"(alias) const walletClient: any\nimport walletClient","start":18,"length":12,"target":"walletClient","line":0,"character":18},{"type":"hover","text":"(alias) const domain: {\n    readonly name: \"Ether Mail\";\n    readonly version: \"1\";\n    readonly chainId: 1;\n    readonly verifyingContract: \"0xCcCCccccCCCCcCCCCCCcCcCccCcCCCcCcccccccC\";\n}\nimport domain","start":58,"length":6,"target":"domain","line":1,"character":9},{"type":"hover","text":"(alias) const types: {\n    readonly Person: readonly [{\n        readonly name: \"name\";\n        readonly type: \"string\";\n    }, {\n        readonly name: \"wallet\";\n        readonly type: \"address\";\n    }];\n    readonly Mail: readonly [{\n        readonly name: \"from\";\n        readonly type: \"Person\";\n    }, {\n        readonly name: \"to\";\n        readonly type: \"Person\";\n    }, {\n        readonly name: \"contents\";\n        readonly type: \"string\";\n    }];\n}\nimport types","start":66,"length":5,"target":"types","line":1,"character":17},{"type":"hover","text":"const signature: any","start":96,"length":9,"target":"signature","line":3,"character":6},{"type":"hover","text":"(alias) const walletClient: any\nimport walletClient","start":114,"length":12,"target":"walletClient","line":3,"character":24},{"type":"hover","text":"any","start":127,"length":13,"target":"signTypedData","line":3,"character":37},{"type":"hover","text":"(property) account: any","start":196,"length":7,"target":"account","line":5,"character":2},{"type":"hover","text":"(property) domain: {\n    readonly name: \"Ether Mail\";\n    readonly version: \"1\";\n    readonly chainId: 1;\n    readonly verifyingContract: \"0xCcCCccccCCCCcCCCCCCcCcCccCcCCCcCcccccccC\";\n}","start":207,"length":6,"target":"domain","line":6,"character":2},{"type":"hover","text":"(property) types: {\n    readonly Person: readonly [{\n        readonly name: \"name\";\n        readonly type: \"string\";\n    }, {\n        readonly name: \"wallet\";\n        readonly type: \"address\";\n    }];\n    readonly Mail: readonly [{\n        readonly name: \"from\";\n        readonly type: \"Person\";\n    }, {\n        readonly name: \"to\";\n        readonly type: \"Person\";\n    }, {\n        readonly name: \"contents\";\n        readonly type: \"string\";\n    }];\n}","start":217,"length":5,"target":"types","line":7,"character":2},{"type":"hover","text":"(property) primaryType: string","start":226,"length":11,"target":"primaryType","line":8,"character":2},{"type":"hover","text":"(property) message: {\n    from: {\n        name: string;\n        wallet: string;\n    };\n    to: {\n        name: string;\n        wallet: string;\n    };\n    contents: string;\n}","start":249,"length":7,"target":"message","line":9,"character":2},{"type":"hover","text":"(property) from: {\n    name: string;\n    wallet: string;\n}","start":264,"length":4,"target":"from","line":10,"character":4},{"type":"hover","text":"(property) name: string","start":278,"length":4,"target":"name","line":11,"character":6},{"type":"hover","text":"(property) wallet: string","start":297,"length":6,"target":"wallet","line":12,"character":6},{"type":"hover","text":"(property) to: {\n    name: string;\n    wallet: string;\n}","start":362,"length":2,"target":"to","line":14,"character":4},{"type":"hover","text":"(property) name: string","start":374,"length":4,"target":"name","line":15,"character":6},{"type":"hover","text":"(property) wallet: string","start":393,"length":6,"target":"wallet","line":16,"character":6},{"type":"hover","text":"(property) contents: string","start":458,"length":8,"target":"contents","line":18,"character":4},{"type":"hover","text":"(property) verifier: string","start":553,"length":8,"target":"verifier","line":21,"character":2}],"tags":[]}