{"code":"const valid = await publicClient.verifyTypedData({\n  address: '0xf39fd6e51aad88f6f4ce6ab8827279cfffb92266',\n  domain: {\n    name: 'Ether Mail',\n    version: '1',\n    chainId: 1,\n    verifyingContract: '0xCcCCccccCCCCcCCCCCCcCcCccCcCCCcCcccccccC',\n  },\n  types: {\n    Person: [\n      { name: 'name', type: 'string' },\n      { name: 'wallet', type: 'address' },\n    ],\n    Mail: [\n      { name: 'from', type: 'Person' },\n      { name: 'to', type: 'Person' },\n      { name: 'contents', type: 'string' },\n    ],\n  },\n  primaryType: 'Mail',\n  message: { // [!code focus:11]\n    from: {\n      name: 'Cow',\n      wallet: '0xCD2a3d9F938E13CD947Ec05AbC7FE734Df8DD826',\n    },\n    to: {\n      name: 'Bob',\n      wallet: '0xbBbBBBBbbBBBbbbBbbBbbbbBBbBbbbbBbBbbBBbB',\n    },\n    contents: 'Hello, Bob!',\n  },\n  signature: '0x...',\n})","nodes":[{"type":"hover","text":"const valid: any","start":6,"length":5,"target":"valid","line":0,"character":6},{"type":"hover","text":"const publicClient: any","start":20,"length":12,"target":"publicClient","line":0,"character":20},{"type":"hover","text":"any","start":33,"length":15,"target":"verifyTypedData","line":0,"character":33},{"type":"hover","text":"(property) address: string","start":53,"length":7,"target":"address","line":1,"character":2},{"type":"hover","text":"(property) domain: {\n    name: string;\n    version: string;\n    chainId: number;\n    verifyingContract: string;\n}","start":110,"length":6,"target":"domain","line":2,"character":2},{"type":"hover","text":"(property) name: string","start":124,"length":4,"target":"name","line":3,"character":4},{"type":"hover","text":"(property) version: string","start":148,"length":7,"target":"version","line":4,"character":4},{"type":"hover","text":"(property) chainId: number","start":166,"length":7,"target":"chainId","line":5,"character":4},{"type":"hover","text":"(property) verifyingContract: string","start":182,"length":17,"target":"verifyingContract","line":6,"character":4},{"type":"hover","text":"(property) types: {\n    Person: {\n        name: string;\n        type: string;\n    }[];\n    Mail: {\n        name: string;\n        type: string;\n    }[];\n}","start":254,"length":5,"target":"types","line":8,"character":2},{"type":"hover","text":"(property) Person: {\n    name: string;\n    type: string;\n}[]","start":267,"length":6,"target":"Person","line":9,"character":4},{"type":"hover","text":"(property) name: string","start":285,"length":4,"target":"name","line":10,"character":8},{"type":"hover","text":"(property) type: string","start":299,"length":4,"target":"type","line":10,"character":22},{"type":"hover","text":"(property) name: string","start":325,"length":4,"target":"name","line":11,"character":8},{"type":"hover","text":"(property) type: string","start":341,"length":4,"target":"type","line":11,"character":24},{"type":"hover","text":"(property) Mail: {\n    name: string;\n    type: string;\n}[]","start":371,"length":4,"target":"Mail","line":13,"character":4},{"type":"hover","text":"(property) name: string","start":387,"length":4,"target":"name","line":14,"character":8},{"type":"hover","text":"(property) type: string","start":401,"length":4,"target":"type","line":14,"character":22},{"type":"hover","text":"(property) name: string","start":427,"length":4,"target":"name","line":15,"character":8},{"type":"hover","text":"(property) type: string","start":439,"length":4,"target":"type","line":15,"character":20},{"type":"hover","text":"(property) name: string","start":465,"length":4,"target":"name","line":16,"character":8},{"type":"hover","text":"(property) type: string","start":483,"length":4,"target":"type","line":16,"character":26},{"type":"hover","text":"(property) primaryType: string","start":515,"length":11,"target":"primaryType","line":19,"character":2},{"type":"hover","text":"(property) message: {\n    from: {\n        name: string;\n        wallet: string;\n    };\n    to: {\n        name: string;\n        wallet: string;\n    };\n    contents: string;\n}","start":538,"length":7,"target":"message","line":20,"character":2},{"type":"hover","text":"(property) from: {\n    name: string;\n    wallet: string;\n}","start":573,"length":4,"target":"from","line":21,"character":4},{"type":"hover","text":"(property) name: string","start":587,"length":4,"target":"name","line":22,"character":6},{"type":"hover","text":"(property) wallet: string","start":606,"length":6,"target":"wallet","line":23,"character":6},{"type":"hover","text":"(property) to: {\n    name: string;\n    wallet: string;\n}","start":671,"length":2,"target":"to","line":25,"character":4},{"type":"hover","text":"(property) name: string","start":683,"length":4,"target":"name","line":26,"character":6},{"type":"hover","text":"(property) wallet: string","start":702,"length":6,"target":"wallet","line":27,"character":6},{"type":"hover","text":"(property) contents: string","start":767,"length":8,"target":"contents","line":29,"character":4},{"type":"hover","text":"(property) signature: string","start":799,"length":9,"target":"signature","line":31,"character":2}],"meta":{"extension":"ts","compilerOptions":{"strict":true,"module":99,"target":99,"allowJs":true,"skipDefaultLibCheck":true,"skipLibCheck":true,"moduleDetection":3,"baseUrl":".","ignoreDeprecations":"5.0","moduleResolution":100,"preserveSymlinks":false,"types":["node"]},"handbookOptions":{"errors":[],"noErrors":true,"noErrorsCutted":false,"noErrorValidation":false,"noStaticSemanticInfo":false,"showEmit":false,"keepNotations":false},"removals":[[0,191]],"flagNotations":[],"virtualFiles":[{"offset":0,"filename":"index.ts","filepath":"../index.ts","content":"import { createPublicClient, http } from 'viem'\nimport { mainnet } from 'viem/chains'\n\nexport const publicClient = createPublicClient({\n  chain: mainnet,\n  transport: http(),\n})\n// ---cut---\nconst valid = await publicClient.verifyTypedData({\n  address: '0xf39fd6e51aad88f6f4ce6ab8827279cfffb92266',\n  domain: {\n    name: 'Ether Mail',\n    version: '1',\n    chainId: 1,\n    verifyingContract: '0xCcCCccccCCCCcCCCCCCcCcCccCcCCCcCcccccccC',\n  },\n  types: {\n    Person: [\n      { name: 'name', type: 'string' },\n      { name: 'wallet', type: 'address' },\n    ],\n    Mail: [\n      { name: 'from', type: 'Person' },\n      { name: 'to', type: 'Person' },\n      { name: 'contents', type: 'string' },\n    ],\n  },\n  primaryType: 'Mail',\n  message: { // [!code focus:11]\n    from: {\n      name: 'Cow',\n      wallet: '0xCD2a3d9F938E13CD947Ec05AbC7FE734Df8DD826',\n    },\n    to: {\n      name: 'Bob',\n      wallet: '0xbBbBBBBbbBBBbbbBbbBbbbbBBbBbbbbBbBbbBBbB',\n    },\n    contents: 'Hello, Bob!',\n  },\n  signature: '0x...',\n})","extension":"ts","supportLsp":true}],"positionQueries":[],"positionCompletions":[],"positionHighlights":[]},"queries":[],"completions":[],"errors":[],"highlights":[],"hovers":[{"type":"hover","text":"const valid: any","start":6,"length":5,"target":"valid","line":0,"character":6},{"type":"hover","text":"const publicClient: any","start":20,"length":12,"target":"publicClient","line":0,"character":20},{"type":"hover","text":"any","start":33,"length":15,"target":"verifyTypedData","line":0,"character":33},{"type":"hover","text":"(property) address: string","start":53,"length":7,"target":"address","line":1,"character":2},{"type":"hover","text":"(property) domain: {\n    name: string;\n    version: string;\n    chainId: number;\n    verifyingContract: string;\n}","start":110,"length":6,"target":"domain","line":2,"character":2},{"type":"hover","text":"(property) name: string","start":124,"length":4,"target":"name","line":3,"character":4},{"type":"hover","text":"(property) version: string","start":148,"length":7,"target":"version","line":4,"character":4},{"type":"hover","text":"(property) chainId: number","start":166,"length":7,"target":"chainId","line":5,"character":4},{"type":"hover","text":"(property) verifyingContract: string","start":182,"length":17,"target":"verifyingContract","line":6,"character":4},{"type":"hover","text":"(property) types: {\n    Person: {\n        name: string;\n        type: string;\n    }[];\n    Mail: {\n        name: string;\n        type: string;\n    }[];\n}","start":254,"length":5,"target":"types","line":8,"character":2},{"type":"hover","text":"(property) Person: {\n    name: string;\n    type: string;\n}[]","start":267,"length":6,"target":"Person","line":9,"character":4},{"type":"hover","text":"(property) name: string","start":285,"length":4,"target":"name","line":10,"character":8},{"type":"hover","text":"(property) type: string","start":299,"length":4,"target":"type","line":10,"character":22},{"type":"hover","text":"(property) name: string","start":325,"length":4,"target":"name","line":11,"character":8},{"type":"hover","text":"(property) type: string","start":341,"length":4,"target":"type","line":11,"character":24},{"type":"hover","text":"(property) Mail: {\n    name: string;\n    type: string;\n}[]","start":371,"length":4,"target":"Mail","line":13,"character":4},{"type":"hover","text":"(property) name: string","start":387,"length":4,"target":"name","line":14,"character":8},{"type":"hover","text":"(property) type: string","start":401,"length":4,"target":"type","line":14,"character":22},{"type":"hover","text":"(property) name: string","start":427,"length":4,"target":"name","line":15,"character":8},{"type":"hover","text":"(property) type: string","start":439,"length":4,"target":"type","line":15,"character":20},{"type":"hover","text":"(property) name: string","start":465,"length":4,"target":"name","line":16,"character":8},{"type":"hover","text":"(property) type: string","start":483,"length":4,"target":"type","line":16,"character":26},{"type":"hover","text":"(property) primaryType: string","start":515,"length":11,"target":"primaryType","line":19,"character":2},{"type":"hover","text":"(property) message: {\n    from: {\n        name: string;\n        wallet: string;\n    };\n    to: {\n        name: string;\n        wallet: string;\n    };\n    contents: string;\n}","start":538,"length":7,"target":"message","line":20,"character":2},{"type":"hover","text":"(property) from: {\n    name: string;\n    wallet: string;\n}","start":573,"length":4,"target":"from","line":21,"character":4},{"type":"hover","text":"(property) name: string","start":587,"length":4,"target":"name","line":22,"character":6},{"type":"hover","text":"(property) wallet: string","start":606,"length":6,"target":"wallet","line":23,"character":6},{"type":"hover","text":"(property) to: {\n    name: string;\n    wallet: string;\n}","start":671,"length":2,"target":"to","line":25,"character":4},{"type":"hover","text":"(property) name: string","start":683,"length":4,"target":"name","line":26,"character":6},{"type":"hover","text":"(property) wallet: string","start":702,"length":6,"target":"wallet","line":27,"character":6},{"type":"hover","text":"(property) contents: string","start":767,"length":8,"target":"contents","line":29,"character":4},{"type":"hover","text":"(property) signature: string","start":799,"length":9,"target":"signature","line":31,"character":2}],"tags":[]}